[
  {
    "label": "Staaf schademeldingen",
    "value": "staaf_schademeldingen",
    "className": "img-custom-graph",
    "scripts": [
      "https://graphs.publikaan.nl/graph-selector/bundle.js"
    ]
  },
  {
    "label" : "Staaf schade-opnames",
    "value" : "staaf_schade-opnames",
    "className": "img-custom-graph",
    "scripts": [
      "https://graphs.publikaan.nl/graph-selector/bundle.js"
    ]
  },
  {
    "label" : "Multistaaf besluiten en afgehandeld",
    "value" : "multistaaf_besluiten_afgehandeld",
    "className": "img-custom-graph",
    "scripts": [
      "https://graphs.publikaan.nl/graph-selector/bundle.js"
    ]
  },
  {
    "label" : "Kaart schademeldingen",
    "value" : "kaart_schademeldingen",
    "className": "img-custom-graph",
    "scripts": [
      "https://graphs.publikaan.nl/graph-selector/bundle.js"
    ]
  },
  {
    "label" : "Taart Bezwaren",
    "value" : "taart_bezwaren",
    "className": "img-custom-graph",
    "scripts": [
      "https://graphs.publikaan.nl/graph-selector/bundle.js"
    ]
  },
  {
    "label" : "Taart Schadevergoedingen",
    "value" : "taart_schadevergoedingen",
    "className": "img-custom-graph",
    "scripts": [
      "https://graphs.publikaan.nl/graph-selector/bundle.js"
    ]
  },
  {
    "label" : "Taart Specials",
    "value" : "taart_specials",
    "className": "img-custom-graph",
    "scripts": [
      "https://graphs.publikaan.nl/graph-selector/bundle.js"
    ]
  },
  {
    "label" : "Bollen",
    "value" : "bollen",
    "className": "img-custom-graph",
    "scripts": [
      "https://graphs.publikaan.nl/graph-selector/bundle.js"
    ]
  },
  {
    "label" : "Trend in behandeling",
    "value" : "trend_in_behandeling",
    "className": "img-custom-graph",
    "scripts": [
      "https://graphs.publikaan.nl/graph-selector/bundle.js"
    ]
  }
]